elysium/__init__.py
elysium/decompile.py
elysium/elysium.py
elysium/query_visitor.py
elysium-0.1.0.dist-info/LICENSE
elysium-0.1.0.dist-info/WHEEL
elysium-0.1.0.dist-info/METADATA
elysium-0.1.0.dist-info/RECORD
